[["kai", {"72/129": {"tf": 1, "body": [26], "head": [], "tf-idf": 1.1139433523068367}, "16/142": {"tf": 1, "body": [36], "head": [], "tf-idf": 1.1139433523068367}, "33/334": {"tf": 1, "body": [187], "head": [], "tf-idf": 1.1139433523068367}, "42/436": {"tf": 2, "body": [644, 648], "head": [], "tf-idf": 1.4492737148216845}, "32/277": {"tf": 1, "body": [268], "head": [], "tf-idf": 1.1139433523068367}, "44/210": {"tf": 1, "body": [150], "head": [], "tf-idf": 1.1139433523068367}, "69/66": {"tf": 2, "body": [71, 121], "head": [], "tf-idf": 1.4492737148216845}, "38/17": {"tf": 4, "body": [559, 682, 730, 794], "head": [], "tf-idf": 1.7846040773365324}, "54/193": {"tf": 4, "body": [390, 421, 498, 647], "head": [], "tf-idf": 1.7846040773365324}, "6/231": {"tf": 1, "body": [13], "head": [], "tf-idf": 1.1139433523068367}, "73/88": {"tf": 1, "body": [172], "head": [], "tf-idf": 1.1139433523068367}, "14/103": {"tf": 3, "body": [463, 3045, 7118], "head": [], "tf-idf": 1.6454294022461016}, "46/388": {"tf": 1, "body": [114], "head": [], "tf-idf": 1.1139433523068367}, "28/341": {"tf": 2, "body": [322, 1092], "head": [], "tf-idf": 1.4492737148216845}, "17/497": {"tf": 1, "body": [5], "head": [], "tf-idf": 1.1139433523068367}, "21/70": {"tf": 1, "body": [1011], "head": [], "tf-idf": 1.1139433523068367}, "34/180": {"tf": 1, "body": [48], "head": [], "tf-idf": 1.1139433523068367}, "47/178": {"tf": 2, "body": [2614, 2628], "head": [], "tf-idf": 1.4492737148216845}, "5/470": {"tf": 1, "body": [1240], "head": [], "tf-idf": 1.1139433523068367}, "27/463": {"tf": 1, "body": [159], "head": [], "tf-idf": 1.1139433523068367}, "43/367": {"tf": 4, "body": [774, 1006, 1158, 1411], "head": [], "tf-idf": 1.7846040773365324}, "5/293": {"tf": 1, "body": [1032], "head": [], "tf-idf": 1.1139433523068367}, "31/59": {"tf": 1, "body": [264], "head": [], "tf-idf": 1.1139433523068367}, "2/429": {"tf": 1, "body": [139], "head": [], "tf-idf": 1.1139433523068367}, "70/182": {"tf": 2, "body": [936, 950], "head": [], "tf-idf": 1.4492737148216845}, "74/420": {"tf": 3, "body": [1309, 1339, 1501], "head": [], "tf-idf": 1.6454294022461016}, "15/400": {"tf": 5, "body": [0, 3, 492, 534, 573], "head": [], "tf-idf": 1.8925563420988256}, "51/249": {"tf": 1, "body": [71], "head": [], "tf-idf": 1.1139433523068367}, "13/474": {"tf": 1, "body": [1150], "head": [], "tf-idf": 1.1139433523068367}, "31/316": {"tf": 2, "body": [534, 557], "head": [], "tf-idf": 1.4492737148216845}, "53/143": {"tf": 1, "body": [21], "head": [], "tf-idf": 1.1139433523068367}, "26/447": {"tf": 3, "body": [2306, 7546, 7838], "head": [], "tf-idf": 1.6454294022461016}, "25/328": {"tf": 2, "body": [0, 2], "head": [], "tf-idf": 1.4492737148216845}, "4/354": {"tf": 1, "body": [843], "head": [], "tf-idf": 1.1139433523068367}, "43/239": {"tf": 1, "body": [443], "head": [], "tf-idf": 1.1139433523068367}, "35/346": {"tf": 1, "body": [170], "head": [], "tf-idf": 1.1139433523068367}, "65/323": {"tf": 3, "body": [1119, 1732, 4752], "head": [], "tf-idf": 1.6454294022461016}, "17/32": {"tf": 2, "body": [148, 180], "head": [], "tf-idf": 1.4492737148216845}, "42/374": {"tf": 1, "body": [170], "head": [], "tf-idf": 1.1139433523068367}, "62/446": {"tf": 1, "body": [683], "head": [], "tf-idf": 1.1139433523068367}, "16/82": {"tf": 2, "body": [2614, 2628], "head": [], "tf-idf": 1.4492737148216845}, "50/309": {"tf": 1, "body": [1240], "head": [], "tf-idf": 1.1139433523068367}, "36/172": {"tf": 3, "body": [84, 338, 406], "head": [], "tf-idf": 1.6454294022461016}, "30/76": {"tf": 2, "body": [350, 1209], "head": [], "tf-idf": 1.4492737148216845}, "2/411": {"tf": 4, "body": [57, 99, 223, 466], "head": [], "tf-idf": 1.7846040773365324}, "19/34": {"tf": 1, "body": [52], "head": [], "tf-idf": 1.1139433523068367}, "0/460": {"tf": 2, "body": [227, 241], "head": [], "tf-idf": 1.4492737148216845}, "5/143": {"tf": 1, "body": [68], "head": [], "tf-idf": 1.1139433523068367}, "2/415": {"tf": 2, "body": [644, 648], "head": [], "tf-idf": 1.4492737148216845}, "8/446": {"tf": 1, "body": [551], "head": [], "tf-idf": 1.1139433523068367}, "25/119": {"tf": 1, "body": [367], "head": [], "tf-idf": 1.1139433523068367}, "34/323": {"tf": 1, "body": [57], "head": [], "tf-idf": 1.1139433523068367}, "50/19": {"tf": 1, "body": [244], "head": [], "tf-idf": 1.1139433523068367}, "49/294": {"tf": 1, "body": [17], "head": [], "tf-idf": 1.1139433523068367}}], ["kaibab", {"24/77": {"tf": 1, "body": [13769], "head": [], "tf-idf": 2.846337112129805}}], ["kaiban", {"14/103": {"tf": 1, "body": [5097], "head": [], "tf-idf": 2.846337112129805}}], ["kaibel", {"72/214": {"tf": 1, "body": [167], "head": [], "tf-idf": 2.846337112129805}}], ["kaibo", {"43/367": {"tf": 1, "body": [107], "head": [], "tf-idf": 2.1473671077937864}, "54/193": {"tf": 1, "body": [282], "head": [], "tf-idf": 2.1473671077937864}, "32/277": {"tf": 1, "body": [856], "head": [], "tf-idf": 2.1473671077937864}, "38/17": {"tf": 1, "body": [396], "head": [], "tf-idf": 2.1473671077937864}, "25/119": {"tf": 1, "body": [542], "head": [], "tf-idf": 2.1473671077937864}}], ["kaifa", {"14/103": {"tf": 6, "body": [3833, 4721, 8592, 8763, 8905, 9355], "head": [], "tf-idf": 5.061217894946982}}], ["kaifang", {"14/103": {"tf": 9, "body": [5112, 5119, 5353, 5460, 5980, 6863, 7149, 7949, 9401], "head": [], "tf-idf": 5.562432980718831}}], ["kaihui", {"14/103": {"tf": 1, "body": [3072], "head": [], "tf-idf": 2.846337112129805}}], ["kail", {"19/336": {"tf": 1, "body": [4048], "head": [], "tf-idf": 2.545307116465824}, "49/410": {"tf": 1, "body": [39683], "head": [], "tf-idf": 2.545307116465824}}], ["kailua", {"28/310": {"tf": 2, "body": [520, 848], "head": [], "tf-idf": 3.0824208966933537}, "31/24": {"tf": 1, "body": [3053], "head": [], "tf-idf": 2.369215857410143}, "69/91": {"tf": 1, "body": [3370], "head": [], "tf-idf": 2.369215857410143}}], ["kaimah", {"24/77": {"tf": 1, "body": [2005], "head": [], "tf-idf": 2.846337112129805}}], ["kaimakam", {"19/336": {"tf": 1, "body": [14032], "head": [], "tf-idf": 2.545307116465824}, "49/410": {"tf": 1, "body": [39684], "head": [], "tf-idf": 2.545307116465824}}], ["kaiman", {"19/336": {"tf": 1, "body": [4114], "head": [], "tf-idf": 2.545307116465824}, "49/410": {"tf": 1, "body": [39685], "head": [], "tf-idf": 2.545307116465824}}], ["kaimenhong", {"14/103": {"tf": 1, "body": [7545], "head": [], "tf-idf": 2.846337112129805}}], ["kaimo", {"14/103": {"tf": 1, "body": [3329], "head": [], "tf-idf": 2.846337112129805}}], ["kaimu", {"14/103": {"tf": 1, "body": [3084], "head": [], "tf-idf": 2.846337112129805}}], ["kain", {"59/310": {"tf": 1, "body": [247], "head": [], "tf-idf": 2.369215857410143}, "31/77": {"tf": 1, "body": [233], "head": [], "tf-idf": 2.369215857410143}, "74/31": {"tf": 3, "body": [273, 385, 595], "head": [], "tf-idf": 3.499619099999391}}], ["kaindl", {"31/24": {"tf": 1, "body": [2852], "head": [], "tf-idf": 2.846337112129805}}], ["kainen", {"63/62": {"tf": 1, "body": [911], "head": [], "tf-idf": 2.846337112129805}}], ["kainingi", {"54/377": {"tf": 1, "body": [83], "head": [], "tf-idf": 1.8920946026904804}, "42/124": {"tf": 1, "body": [103], "head": [], "tf-idf": 1.8920946026904804}, "44/202": {"tf": 1, "body": [445], "head": [], "tf-idf": 1.8920946026904804}, "31/345": {"tf": 1, "body": [373], "head": [], "tf-idf": 1.8920946026904804}, "37/182": {"tf": 2, "body": [10, 22], "head": [], "tf-idf": 2.461671832734238}, "34/195": {"tf": 2, "body": [10, 22], "head": [], "tf-idf": 2.461671832734238}, "44/31": {"tf": 1, "body": [103], "head": [], "tf-idf": 1.8920946026904804}, "62/324": {"tf": 2, "body": [10, 22], "head": [], "tf-idf": 2.461671832734238}, "16/367": {"tf": 1, "body": [103], "head": [], "tf-idf": 1.8920946026904804}}], ["kainit", {"19/336": {"tf": 1, "body": [19454], "head": [], "tf-idf": 2.545307116465824}, "49/410": {"tf": 1, "body": [39686], "head": [], "tf-idf": 2.545307116465824}}], ["kainozo", {"19/336": {"tf": 1, "body": [34748], "head": [], "tf-idf": 2.545307116465824}, "49/410": {"tf": 1, "body": [39687], "head": [], "tf-idf": 2.545307116465824}}], ["kainulainen", {"65/483": {"tf": 1, "body": [335], "head": [], "tf-idf": 2.846337112129805}}], ["kaiquan", {"3/382": {"tf": 1, "body": [8899], "head": [], "tf-idf": 1.3022690677795297}, "71/451": {"tf": 1, "body": [8659], "head": [], "tf-idf": 1.3022690677795297}, "73/404": {"tf": 1, "body": [8573], "head": [], "tf-idf": 1.3022690677795297}, "10/305": {"tf": 1, "body": [8664], "head": [], "tf-idf": 1.3022690677795297}, "6/189": {"tf": 1, "body": [8625], "head": [], "tf-idf": 1.3022690677795297}, "64/14": {"tf": 1, "body": [8925], "head": [], "tf-idf": 1.3022690677795297}, "7/313": {"tf": 1, "body": [9707], "head": [], "tf-idf": 1.3022690677795297}, "50/217": {"tf": 1, "body": [8589], "head": [], "tf-idf": 1.3022690677795297}, "46/479": {"tf": 1, "body": [9039], "head": [], "tf-idf": 1.3022690677795297}, "60/23": {"tf": 1, "body": [8589], "head": [], "tf-idf": 1.3022690677795297}, "74/49": {"tf": 1, "body": [8569], "head": [], "tf-idf": 1.3022690677795297}, "8/115": {"tf": 1, "body": [8573], "head": [], "tf-idf": 1.3022690677795297}, "49/41": {"tf": 1, "body": [8578], "head": [], "tf-idf": 1.3022690677795297}, "29/93": {"tf": 1, "body": [8537], "head": [], "tf-idf": 1.3022690677795297}, "43/362": {"tf": 1, "body": [8631], "head": [], "tf-idf": 1.3022690677795297}, "30/347": {"tf": 1, "body": [8591], "head": [], "tf-idf": 1.3022690677795297}, "20/166": {"tf": 1, "body": [8631], "head": [], "tf-idf": 1.3022690677795297}, "18/15": {"tf": 1, "body": [8948], "head": [], "tf-idf": 1.3022690677795297}, "29/189": {"tf": 1, "body": [8618], "head": [], "tf-idf": 1.3022690677795297}, "40/117": {"tf": 1, "body": [8617], "head": [], "tf-idf": 1.3022690677795297}, "35/286": {"tf": 1, "body": [8536], "head": [], "tf-idf": 1.3022690677795297}, "24/95": {"tf": 1, "body": [8658], "head": [], "tf-idf": 1.3022690677795297}, "32/479": {"tf": 1, "body": [8595], "head": [], "tf-idf": 1.3022690677795297}, "23/162": {"tf": 1, "body": [8893], "head": [], "tf-idf": 1.3022690677795297}, "51/51": {"tf": 1, "body": [8700], "head": [], "tf-idf": 1.3022690677795297}, "13/104": {"tf": 1, "body": [8806], "head": [], "tf-idf": 1.3022690677795297}, "29/494": {"tf": 1, "body": [8760], "head": [], "tf-idf": 1.3022690677795297}, "7/329": {"tf": 1, "body": [9545], "head": [], "tf-idf": 1.3022690677795297}, "51/24": {"tf": 1, "body": [8537], "head": [], "tf-idf": 1.3022690677795297}, "60/410": {"tf": 1, "body": [9061], "head": [], "tf-idf": 1.3022690677795297}, "68/42": {"tf": 1, "body": [8705], "head": [], "tf-idf": 1.3022690677795297}, "8/443": {"tf": 1, "body": [9451], "head": [], "tf-idf": 1.3022690677795297}, "0/464": {"tf": 1, "body": [9435], "head": [], "tf-idf": 1.3022690677795297}, "54/325": {"tf": 1, "body": [10078], "head": [], "tf-idf": 1.3022690677795297}, "70/55": {"tf": 1, "body": [8805], "head": [], "tf-idf": 1.3022690677795297}}], ["kair", {"44/202": {"tf": 1, "body": [415], "head": [], "tf-idf": 2.846337112129805}}], ["kairin", {"19/336": {"tf": 1, "body": [19465], "head": [], "tf-idf": 2.545307116465824}, "49/410": {"tf": 1, "body": [39688], "head": [], "tf-idf": 2.545307116465824}}], ["kaiser", {"54/286": {"tf": 2, "body": [3559, 3562], "head": [], "tf-idf": 1.7106699518535056}, "65/485": {"tf": 1, "body": [617], "head": [], "tf-idf": 1.3148581950875502}, "72/269": {"tf": 4, "body": [470, 499, 1879, 2020], "head": [], "tf-idf": 2.106481708619461}, "31/203": {"tf": 2, "body": [398, 564], "head": [], "tf-idf": 1.7106699518535056}, "55/190": {"tf": 2, "body": [3277, 3280], "head": [], "tf-idf": 1.7106699518535056}, "8/184": {"tf": 2, "body": [3703, 3706], "head": [], "tf-idf": 1.7106699518535056}, "44/424": {"tf": 2, "body": [27076, 27789], "head": [], "tf-idf": 1.7106699518535056}, "66/20": {"tf": 2, "body": [1848, 1851], "head": [], "tf-idf": 1.7106699518535056}, "3/175": {"tf": 1, "body": [40], "head": [], "tf-idf": 1.3148581950875502}, "53/333": {"tf": 3, "body": [30, 93, 336], "head": [], "tf-idf": 1.9422049869061528}, "42/45": {"tf": 1, "body": [740], "head": [], "tf-idf": 1.3148581950875502}, "14/434": {"tf": 1, "body": [181], "head": [], "tf-idf": 1.3148581950875502}, "14/223": {"tf": 6, "body": [174, 228, 256, 321, 428, 705], "head": [], "tf-idf": 2.3380167436721084}, "19/336": {"tf": 1, "body": [4322], "head": [], "tf-idf": 1.3148581950875502}, "20/182": {"tf": 2, "body": [3277, 3280], "head": [], "tf-idf": 1.7106699518535056}, "54/276": {"tf": 1, "body": [391], "head": [], "tf-idf": 1.3148581950875502}, "12/360": {"tf": 1, "body": [212], "head": [], "tf-idf": 1.3148581950875502}, "73/311": {"tf": 2, "body": [249, 272], "head": [], "tf-idf": 1.7106699518535056}, "10/407": {"tf": 2, "body": [3212, 3215], "head": [], "tf-idf": 1.7106699518535056}, "14/2": {"tf": 2, "body": [3133, 3136], "head": [], "tf-idf": 1.7106699518535056}, "26/447": {"tf": 1, "body": [3614], "head": [], "tf-idf": 1.3148581950875502}, "24/93": {"tf": 1, "body": [493], "head": [], "tf-idf": 1.3148581950875502}, "11/136": {"tf": 2, "body": [3322, 3325], "head": [], "tf-idf": 1.7106699518535056}, "20/20": {"tf": 2, "body": [1097, 7551], "head": [], "tf-idf": 1.7106699518535056}, "55/170": {"tf": 2, "body": [3275, 3278], "head": [], "tf-idf": 1.7106699518535056}, "59/230": {"tf": 3, "body": [163, 348, 378], "head": [], "tf-idf": 1.9422049869061528}, "29/101": {"tf": 2, "body": [195, 4101], "head": [], "tf-idf": 1.7106699518535056}, "24/142": {"tf": 2, "body": [3072, 3075], "head": [], "tf-idf": 1.7106699518535056}, "67/99": {"tf": 1, "body": [393], "head": [], "tf-idf": 1.3148581950875502}, "5/422": {"tf": 1, "body": [27], "head": [], "tf-idf": 1.3148581950875502}, "49/410": {"tf": 1, "body": [39689], "head": [], "tf-idf": 1.3148581950875502}, "28/289": {"tf": 2, "body": [3401, 3404], "head": [], "tf-idf": 1.7106699518535056}, "40/246": {"tf": 1, "body": [919], "head": [], "tf-idf": 1.3148581950875502}, "5/301": {"tf": 1, "body": [464], "head": [], "tf-idf": 1.3148581950875502}}], ["kaisernahid", {"53/333": {"tf": 1, "body": [39], "head": [], "tf-idf": 2.545307116465824}, "5/422": {"tf": 1, "body": [36], "head": [], "tf-idf": 2.545307116465824}}], ["kaiserslautern", {"11/226": {"tf": 3, "body": [1, 5, 11], "head": [], "tf-idf": 2.9560727691973323}, "39/201": {"tf": 1, "body": [5], "head": [], "tf-idf": 2.0012390721155486}, "41/399": {"tf": 2, "body": [3408, 3932], "head": [], "tf-idf": 2.603672061317082}, "23/419": {"tf": 1, "body": [60], "head": [], "tf-idf": 2.0012390721155486}, "28/310": {"tf": 1, "body": [2005], "head": [], "tf-idf": 2.0012390721155486}, "36/293": {"tf": 2, "body": [1, 5], "head": [], "tf-idf": 2.603672061317082}, "63/154": {"tf": 1, "body": [5], "head": [], "tf-idf": 2.0012390721155486}}], ["kaishi", {"14/103": {"tf": 13, "body": [1136, 1191, 1453, 2364, 2751, 6218, 6222, 6228, 7485, 7515, 7837, 8683, 9495], "head": [], "tf-idf": 6.016995416611041}}], ["kaist", {"66/368": {"tf": 1, "body": [866], "head": [], "tf-idf": 2.0012390721155486}, "72/21": {"tf": 2, "body": [4, 10], "head": [], "tf-idf": 2.603672061317082}, "22/207": {"tf": 1, "body": [85], "head": [], "tf-idf": 2.0012390721155486}, "59/285": {"tf": 1, "body": [741], "head": [], "tf-idf": 2.0012390721155486}, "41/399": {"tf": 1, "body": [1565], "head": [], "tf-idf": 2.0012390721155486}, "16/484": {"tf": 1, "body": [171], "head": [], "tf-idf": 2.0012390721155486}, "52/391": {"tf": 1, "body": [10950], "head": [], "tf-idf": 2.0012390721155486}}], ["kaitlin", {"14/314": {"tf": 2, "body": [644, 710], "head": [], "tf-idf": 2.603672061317082}, "27/225": {"tf": 2, "body": [646, 712], "head": [], "tf-idf": 2.603672061317082}, "68/72": {"tf": 2, "body": [103, 169], "head": [], "tf-idf": 2.603672061317082}, "7/472": {"tf": 2, "body": [644, 710], "head": [], "tf-idf": 2.603672061317082}, "10/367": {"tf": 1, "body": [3951], "head": [], "tf-idf": 2.0012390721155486}, "18/497": {"tf": 2, "body": [644, 710], "head": [], "tf-idf": 2.603672061317082}, "70/463": {"tf": 2, "body": [644, 710], "head": [], "tf-idf": 2.603672061317082}}], ["kaitlyn", {"26/447": {"tf": 1, "body": [6565], "head": [], "tf-idf": 2.846337112129805}}], ["kaitong", {"14/103": {"tf": 1, "body": [4479], "head": [], "tf-idf": 2.846337112129805}}], ["kaituo", {"14/103": {"tf": 2, "body": [6247, 9146], "head": [], "tf-idf": 3.703169960652469}}], ["kaivatutsivut", {"27/201": {"tf": 1, "body": [130], "head": [], "tf-idf": 2.846337112129805}}], ["kaiwan", {"0/379": {"tf": 1, "body": [263], "head": [], "tf-idf": 2.846337112129805}}], ["kaix", {"14/103": {"tf": 1, "body": [506], "head": [], "tf-idf": 2.846337112129805}}], ["kaiy", {"14/103": {"tf": 1, "body": [4084], "head": [], "tf-idf": 2.846337112129805}}], ["kaiyi", {"73/164": {"tf": 1, "body": [39], "head": [], "tf-idf": 2.545307116465824}, "61/146": {"tf": 1, "body": [220], "head": [], "tf-idf": 2.545307116465824}}], ["kaiyong", {"14/103": {"tf": 1, "body": [4470], "head": [], "tf-idf": 2.846337112129805}}], ["kaiyu", {"67/483": {"tf": 2, "body": [2436, 2576], "head": [], "tf-idf": 2.9198718527455942}, "30/76": {"tf": 1, "body": [1132], "head": [], "tf-idf": 2.244277120801843}, "50/344": {"tf": 1, "body": [367], "head": [], "tf-idf": 2.244277120801843}, "28/341": {"tf": 1, "body": [1024], "head": [], "tf-idf": 2.244277120801843}}], ["kaizhan", {"14/103": {"tf": 6, "body": [1628, 3147, 3476, 7290, 9116, 9471], "head": [], "tf-idf": 5.061217894946982}}], ["kaizhi", {"14/103": {"tf": 2, "body": [8277, 10176], "head": [], "tf-idf": 3.703169960652469}}], ["kaizhu", {"4/354": {"tf": 1, "body": [284], "head": [], "tf-idf": 2.244277120801843}, "50/309": {"tf": 1, "body": [229], "head": [], "tf-idf": 2.244277120801843}, "5/293": {"tf": 1, "body": [697], "head": [], "tf-idf": 2.244277120801843}, "5/470": {"tf": 1, "body": [229], "head": [], "tf-idf": 2.244277120801843}}]]