[["zik8", {"43/312": {"tf": 1, "body": [16], "head": [], "tf-idf": 2.846337112129805}}], ["zika", {"7/410": {"tf": 1, "body": [12768], "head": [], "tf-idf": 2.369215857410143}, "36/64": {"tf": 1, "body": [8287], "head": [], "tf-idf": 2.369215857410143}, "72/435": {"tf": 6, "body": [622, 645, 673, 683, 707, 717], "head": [], "tf-idf": 4.212824139282602}}], ["zikatanov", {"16/304": {"tf": 1, "body": [22], "head": [], "tf-idf": 2.369215857410143}, "65/323": {"tf": 1, "body": [4778], "head": [], "tf-idf": 2.369215857410143}, "48/383": {"tf": 1, "body": [15], "head": [], "tf-idf": 2.369215857410143}}], ["zikova", {"3/296": {"tf": 2, "body": [118, 158], "head": [], "tf-idf": 3.703169960652469}}]]