[["mhc", {"33/13": {"tf": 2, "body": [396, 1746], "head": [], "tf-idf": 2.7937890189419257}, "2/227": {"tf": 1, "body": [1133], "head": [], "tf-idf": 2.1473671077937864}, "24/403": {"tf": 6, "body": [751, 755, 3885, 3889, 4239, 4243], "head": [], "tf-idf": 3.8183435077562295}, "2/388": {"tf": 1, "body": [865], "head": [], "tf-idf": 2.1473671077937864}, "64/343": {"tf": 4, "body": [2081, 6951, 6954, 6958], "head": [], "tf-idf": 3.4402109300900654}}], ["mhcid", {"27/83": {"tf": 3, "body": [2, 15, 79], "head": [], "tf-idf": 2.3501953486710287}, "13/462": {"tf": 2, "body": [2, 15], "head": [], "tf-idf": 2.0700227787808}, "3/420": {"tf": 5, "body": [2, 15, 38, 67, 337], "head": [], "tf-idf": 2.703171042298697}, "48/77": {"tf": 3, "body": [1, 14, 156], "head": [], "tf-idf": 2.3501953486710287}, "8/180": {"tf": 9, "body": [0, 3, 16, 34, 37, 41, 93, 158, 185], "head": [], "tf-idf": 3.109326090315559}, "49/210": {"tf": 1, "body": [298], "head": [], "tf-idf": 1.591064607026499}, "27/347": {"tf": 1, "body": [298], "head": [], "tf-idf": 1.591064607026499}, "43/148": {"tf": 4, "body": [1, 14, 46, 184], "head": [], "tf-idf": 2.548980950535101}, "31/138": {"tf": 1, "body": [221], "head": [], "tf-idf": 1.591064607026499}, "22/498": {"tf": 5, "body": [3, 16, 49, 71, 120], "head": [], "tf-idf": 2.703171042298697}, "38/326": {"tf": 3, "body": [2, 15, 93], "head": [], "tf-idf": 2.3501953486710287}, "70/357": {"tf": 1, "body": [221], "head": [], "tf-idf": 1.591064607026499}, "22/33": {"tf": 2, "body": [3, 16], "head": [], "tf-idf": 2.0700227787808}, "21/499": {"tf": 4, "body": [1, 14, 35, 374], "head": [], "tf-idf": 2.548980950535101}, "32/35": {"tf": 12, "body": [0, 7, 19, 62, 79, 102, 128, 176, 177, 189, 224, 304], "head": [], "tf-idf": 3.308111692179631}, "39/415": {"tf": 5, "body": [2, 15, 60, 134, 211], "head": [], "tf-idf": 2.703171042298697}, "55/8": {"tf": 1, "body": [249], "head": [], "tf-idf": 1.591064607026499}, "63/5": {"tf": 5, "body": [2, 15, 53, 156, 334], "head": [], "tf-idf": 2.703171042298697}}], ["mhciddirector", {"27/83": {"tf": 1, "body": [85], "head": [], "tf-idf": 1.8463371121298053}, "3/420": {"tf": 1, "body": [343], "head": [], "tf-idf": 1.8463371121298053}, "48/77": {"tf": 1, "body": [162], "head": [], "tf-idf": 1.8463371121298053}, "8/180": {"tf": 1, "body": [114], "head": [], "tf-idf": 1.8463371121298053}, "22/498": {"tf": 1, "body": [185], "head": [], "tf-idf": 1.8463371121298053}, "38/326": {"tf": 1, "body": [95], "head": [], "tf-idf": 1.8463371121298053}, "21/499": {"tf": 1, "body": [387], "head": [], "tf-idf": 1.8463371121298053}, "32/35": {"tf": 2, "body": [134, 320], "head": [], "tf-idf": 2.4021399649884883}, "39/415": {"tf": 1, "body": [290], "head": [], "tf-idf": 1.8463371121298053}, "63/5": {"tf": 1, "body": [59], "head": [], "tf-idf": 1.8463371121298053}}]]