[["bip", {"1/335": {"tf": 1, "body": [1013], "head": [], "tf-idf": 1.8920946026904804}, "49/140": {"tf": 1, "body": [630], "head": [], "tf-idf": 1.8920946026904804}, "13/61": {"tf": 1, "body": [758], "head": [], "tf-idf": 1.8920946026904804}, "4/366": {"tf": 1, "body": [2857], "head": [], "tf-idf": 1.8920946026904804}, "44/374": {"tf": 1, "body": [472], "head": [], "tf-idf": 1.8920946026904804}, "44/425": {"tf": 1, "body": [413], "head": [], "tf-idf": 1.8920946026904804}, "74/186": {"tf": 1, "body": [860], "head": [], "tf-idf": 1.8920946026904804}, "22/446": {"tf": 1, "body": [105], "head": [], "tf-idf": 1.8920946026904804}, "65/486": {"tf": 1, "body": [379], "head": [], "tf-idf": 1.8920946026904804}}], ["bipalm", {"19/336": {"tf": 1, "body": [15454], "head": [], "tf-idf": 2.545307116465824}, "49/410": {"tf": 1, "body": [7075], "head": [], "tf-idf": 2.545307116465824}}], ["bipar", {"19/336": {"tf": 1, "body": [46223], "head": [], "tf-idf": 2.369215857410143}, "56/20": {"tf": 1, "body": [64], "head": [], "tf-idf": 2.369215857410143}, "49/410": {"tf": 1, "body": [7076], "head": [], "tf-idf": 2.369215857410143}}], ["bipart", {"19/336": {"tf": 1, "body": [25618], "head": [], "tf-idf": 2.545307116465824}, "49/410": {"tf": 1, "body": [7077], "head": [], "tf-idf": 2.545307116465824}}], ["biparti", {"19/336": {"tf": 1, "body": [26304], "head": [], "tf-idf": 2.545307116465824}, "49/410": {"tf": 1, "body": [7078], "head": [], "tf-idf": 2.545307116465824}}], ["bipartit", {"22/183": {"tf": 1, "body": [31], "head": [], "tf-idf": 0.6849691098948304}, "70/408": {"tf": 1, "body": [2061], "head": [], "tf-idf": 0.6849691098948304}, "25/231": {"tf": 2, "body": [28, 37], "head": [], "tf-idf": 0.8911653580764323}, "53/54": {"tf": 1, "body": [71], "head": [], "tf-idf": 0.6849691098948304}, "68/422": {"tf": 1, "body": [50], "head": [], "tf-idf": 0.6849691098948304}, "65/325": {"tf": 1, "body": [115], "head": [], "tf-idf": 0.6849691098948304}, "16/96": {"tf": 1, "body": [140], "head": [], "tf-idf": 0.6849691098948304}, "2/490": {"tf": 2, "body": [21, 174], "head": [], "tf-idf": 0.8911653580764323}, "52/257": {"tf": 1, "body": [48], "head": [], "tf-idf": 0.6849691098948304}, "32/273": {"tf": 4, "body": [77, 85, 94, 102], "head": [], "tf-idf": 1.0973616062580343}, "7/359": {"tf": 1, "body": [994], "head": [], "tf-idf": 0.6849691098948304}, "42/48": {"tf": 1, "body": [2702], "head": [], "tf-idf": 0.6849691098948304}, "2/388": {"tf": 1, "body": [1036], "head": [], "tf-idf": 0.6849691098948304}, "16/412": {"tf": 8, "body": [1274, 1282, 1320, 1366, 12681, 13262, 13270, 13294], "head": [], "tf-idf": 1.303557854439636}, "44/171": {"tf": 1, "body": [75], "head": [], "tf-idf": 0.6849691098948304}, "25/344": {"tf": 2, "body": [22, 43], "head": [], "tf-idf": 0.8911653580764323}, "60/217": {"tf": 5, "body": [384, 531, 556, 562, 956], "head": [], "tf-idf": 1.1637419716080588}, "48/69": {"tf": 1, "body": [12], "head": [], "tf-idf": 0.6849691098948304}, "49/147": {"tf": 5, "body": [291, 305, 331, 366, 421], "head": [], "tf-idf": 1.1637419716080588}, "71/431": {"tf": 12, "body": [441, 544, 569, 575, 1575, 1777, 1785, 3139, 3216, 3261, 3290, 4124], "head": [], "tf-idf": 1.4241749274152662}, "31/425": {"tf": 4, "body": [5286, 5701, 5746, 5775], "head": [], "tf-idf": 1.0973616062580343}, "70/155": {"tf": 1, "body": [21], "head": [], "tf-idf": 0.6849691098948304}, "21/281": {"tf": 2, "body": [3, 10], "head": [], "tf-idf": 0.8911653580764323}, "31/423": {"tf": 1, "body": [535], "head": [], "tf-idf": 0.6849691098948304}, "65/26": {"tf": 1, "body": [27], "head": [], "tf-idf": 0.6849691098948304}, "39/102": {"tf": 1, "body": [42], "head": [], "tf-idf": 0.6849691098948304}, "42/314": {"tf": 5, "body": [288, 336, 564, 615, 651], "head": [], "tf-idf": 1.1637419716080588}, "11/374": {"tf": 3, "body": [88, 94, 132], "head": [], "tf-idf": 1.0117824310520622}, "54/435": {"tf": 1, "body": [14], "head": [], "tf-idf": 0.6849691098948304}, "7/183": {"tf": 1, "body": [31], "head": [], "tf-idf": 0.6849691098948304}, "66/17": {"tf": 1, "body": [1339], "head": [], "tf-idf": 0.6849691098948304}, "20/321": {"tf": 1, "body": [101], "head": [], "tf-idf": 0.6849691098948304}, "6/139": {"tf": 1, "body": [208], "head": [], "tf-idf": 0.6849691098948304}, "49/410": {"tf": 1, "body": [7079], "head": [], "tf-idf": 0.6849691098948304}, "36/442": {"tf": 2, "body": [3, 12], "head": [], "tf-idf": 0.8911653580764323}, "13/312": {"tf": 2, "body": [2], "head": [2], "tf-idf": 0.8911653580764323}, "74/185": {"tf": 1, "body": [12], "head": [], "tf-idf": 0.6849691098948304}, "55/343": {"tf": 3, "body": [218, 223, 374], "head": [], "tf-idf": 1.0117824310520622}, "40/387": {"tf": 3, "body": [301, 304, 428], "head": [], "tf-idf": 1.0117824310520622}, "18/285": {"tf": 3, "body": [6, 118, 551], "head": [], "tf-idf": 1.0117824310520622}, "9/31": {"tf": 1, "body": [737], "head": [], "tf-idf": 0.6849691098948304}, "41/340": {"tf": 3, "body": [528, 602, 610], "head": [], "tf-idf": 1.0117824310520622}, "13/87": {"tf": 1, "body": [782], "head": [], "tf-idf": 0.6849691098948304}, "34/463": {"tf": 1, "body": [271], "head": [], "tf-idf": 0.6849691098948304}, "69/293": {"tf": 2, "body": [174, 223], "head": [], "tf-idf": 0.8911653580764323}, "69/299": {"tf": 1, "body": [102], "head": [], "tf-idf": 0.6849691098948304}, "62/242": {"tf": 1, "body": [97], "head": [], "tf-idf": 0.6849691098948304}, "62/166": {"tf": 1, "body": [44], "head": [], "tf-idf": 0.6849691098948304}, "46/261": {"tf": 2, "body": [402, 459], "head": [], "tf-idf": 0.8911653580764323}, "32/89": {"tf": 4, "body": [284, 286, 293, 295], "head": [], "tf-idf": 1.0973616062580343}, "32/425": {"tf": 1, "body": [448], "head": [], "tf-idf": 0.6849691098948304}, "30/437": {"tf": 10, "body": [0, 25, 60, 62, 72, 82, 100, 109, 116, 141], "head": [], "tf-idf": 1.3699382197896608}, "69/87": {"tf": 1, "body": [12309], "head": [], "tf-idf": 0.6849691098948304}, "64/241": {"tf": 1, "body": [66], "head": [], "tf-idf": 0.6849691098948304}, "69/369": {"tf": 5, "body": [148, 194, 219, 225, 648], "head": [], "tf-idf": 1.1637419716080588}, "68/136": {"tf": 1, "body": [341], "head": [], "tf-idf": 0.6849691098948304}, "67/4": {"tf": 1, "body": [4089], "head": [], "tf-idf": 0.6849691098948304}, "54/491": {"tf": 4, "body": [774, 1248, 1293, 1322], "head": [], "tf-idf": 1.0973616062580343}, "67/343": {"tf": 1, "body": [15], "head": [], "tf-idf": 0.6849691098948304}, "61/285": {"tf": 1, "body": [133], "head": [], "tf-idf": 0.6849691098948304}, "13/474": {"tf": 1, "body": [1807], "head": [], "tf-idf": 0.6849691098948304}, "52/132": {"tf": 11, "body": [2875, 5541, 6579, 6759, 7019, 8129, 8138, 8147, 10121, 10132, 13253], "head": [], "tf-idf": 1.3982909304986473}, "2/138": {"tf": 2, "body": [42, 50], "head": [], "tf-idf": 0.8911653580764323}, "13/479": {"tf": 1, "body": [44], "head": [], "tf-idf": 0.6849691098948304}, "39/128": {"tf": 1, "body": [257], "head": [], "tf-idf": 0.6849691098948304}, "64/343": {"tf": 1, "body": [7623], "head": [], "tf-idf": 0.6849691098948304}, "62/278": {"tf": 1, "body": [6], "head": [], "tf-idf": 0.6849691098948304}, "49/123": {"tf": 4, "body": [49, 95, 115, 119], "head": [], "tf-idf": 1.0973616062580343}, "35/322": {"tf": 1, "body": [23], "head": [], "tf-idf": 0.6849691098948304}, "5/37": {"tf": 10, "body": [603, 974, 999, 1005, 2112, 2381, 2389, 4006, 4051, 4080], "head": [], "tf-idf": 1.3699382197896608}, "54/33": {"tf": 1, "body": [158], "head": [], "tf-idf": 0.6849691098948304}, "27/151": {"tf": 13, "body": [4348, 5374, 5399, 5405, 8253, 8840, 8848, 13395, 13978, 14023, 14052, 14704, 16008], "head": [], "tf-idf": 1.447985896397708}, "59/463": {"tf": 1, "body": [150], "head": [], "tf-idf": 0.6849691098948304}, "46/496": {"tf": 1, "body": [27], "head": [], "tf-idf": 0.6849691098948304}, "65/99": {"tf": 6, "body": [993, 1095, 1103, 1263, 1308, 1337], "head": [], "tf-idf": 1.217978679233664}, "18/203": {"tf": 1, "body": [32], "head": [], "tf-idf": 0.6849691098948304}, "25/396": {"tf": 3, "body": [250, 255, 429], "head": [], "tf-idf": 1.0117824310520622}, "28/320": {"tf": 1, "body": [149], "head": [], "tf-idf": 0.6849691098948304}, "64/292": {"tf": 5, "body": [43, 49, 54, 58, 82], "head": [], "tf-idf": 1.1637419716080588}, "26/245": {"tf": 1, "body": [254], "head": [], "tf-idf": 0.6849691098948304}, "3/145": {"tf": 1, "body": [99], "head": [], "tf-idf": 0.6849691098948304}, "44/141": {"tf": 1, "body": [9], "head": [], "tf-idf": 0.6849691098948304}, "33/420": {"tf": 1, "body": [1200], "head": [], "tf-idf": 0.6849691098948304}, "43/7": {"tf": 8, "body": [1471, 1597, 2094, 2365, 3714, 7934, 9846, 10662], "head": [], "tf-idf": 1.303557854439636}, "25/141": {"tf": 2, "body": [6629, 6631], "head": [], "tf-idf": 0.8911653580764323}, "55/279": {"tf": 3, "body": [79, 95, 121], "head": [], "tf-idf": 1.0117824310520622}, "50/391": {"tf": 1, "body": [29], "head": [], "tf-idf": 0.6849691098948304}, "19/336": {"tf": 1, "body": [28358], "head": [], "tf-idf": 0.6849691098948304}, "1/455": {"tf": 4, "body": [355, 458, 503, 532], "head": [], "tf-idf": 1.0973616062580343}, "34/97": {"tf": 3, "body": [10, 55, 84], "head": [], "tf-idf": 1.0117824310520622}, "12/25": {"tf": 1, "body": [317], "head": [], "tf-idf": 0.6849691098948304}, "27/427": {"tf": 2, "body": [229, 1128], "head": [], "tf-idf": 0.8911653580764323}, "37/283": {"tf": 1, "body": [66], "head": [], "tf-idf": 0.6849691098948304}, "73/474": {"tf": 4, "body": [79, 87, 96, 98], "head": [], "tf-idf": 1.0973616062580343}, "57/336": {"tf": 1, "body": [68], "head": [], "tf-idf": 0.6849691098948304}, "34/440": {"tf": 1, "body": [12], "head": [], "tf-idf": 0.6849691098948304}, "34/328": {"tf": 1, "body": [66], "head": [], "tf-idf": 0.6849691098948304}, "41/373": {"tf": 2, "body": [192, 303], "head": [], "tf-idf": 0.8911653580764323}, "73/435": {"tf": 3, "body": [223, 228, 385], "head": [], "tf-idf": 1.0117824310520622}, "35/190": {"tf": 1, "body": [1313], "head": [], "tf-idf": 0.6849691098948304}, "71/23": {"tf": 2, "body": [4, 11], "head": [], "tf-idf": 0.8911653580764323}, "29/278": {"tf": 1, "body": [101], "head": [], "tf-idf": 0.6849691098948304}, "12/464": {"tf": 4, "body": [345, 348, 444, 486], "head": [], "tf-idf": 1.0973616062580343}, "2/292": {"tf": 2, "body": [117, 953], "head": [], "tf-idf": 0.8911653580764323}, "22/412": {"tf": 1, "body": [21], "head": [], "tf-idf": 0.6849691098948304}, "18/340": {"tf": 10, "body": [11555, 11782, 13267, 13410, 13447, 13467, 13533, 13543, 20845, 25538], "head": [], "tf-idf": 1.3699382197896608}, "40/57": {"tf": 1, "body": [94], "head": [], "tf-idf": 0.6849691098948304}, "24/387": {"tf": 1, "body": [820], "head": [], "tf-idf": 0.6849691098948304}, "30/468": {"tf": 1, "body": [163], "head": [], "tf-idf": 0.6849691098948304}, "12/35": {"tf": 3, "body": [1575, 1620, 1649], "head": [], "tf-idf": 1.0117824310520622}, "48/471": {"tf": 1, "body": [177], "head": [], "tf-idf": 0.6849691098948304}, "58/331": {"tf": 3, "body": [7, 32, 38], "head": [], "tf-idf": 1.0117824310520622}, "71/314": {"tf": 1, "body": [65], "head": [], "tf-idf": 0.6849691098948304}, "30/150": {"tf": 3, "body": [336, 339, 473], "head": [], "tf-idf": 1.0117824310520622}, "14/26": {"tf": 1, "body": [42], "head": [], "tf-idf": 0.6849691098948304}, "23/193": {"tf": 2, "body": [269, 271], "head": [], "tf-idf": 0.8911653580764323}, "30/394": {"tf": 2, "body": [6382, 6560], "head": [], "tf-idf": 0.8911653580764323}, "16/489": {"tf": 1, "body": [56], "head": [], "tf-idf": 0.6849691098948304}, "35/151": {"tf": 3, "body": [2, 9, 22], "head": [], "tf-idf": 1.0117824310520622}, "45/26": {"tf": 1, "body": [12], "head": [], "tf-idf": 0.6849691098948304}, "46/57": {"tf": 1, "body": [71], "head": [], "tf-idf": 0.6849691098948304}, "30/248": {"tf": 1, "body": [25], "head": [], "tf-idf": 0.6849691098948304}, "36/254": {"tf": 1, "body": [247], "head": [], "tf-idf": 0.6849691098948304}, "45/191": {"tf": 1, "body": [16], "head": [], "tf-idf": 0.6849691098948304}, "30/243": {"tf": 1, "body": [190], "head": [], "tf-idf": 0.6849691098948304}, "63/464": {"tf": 5, "body": [43, 48, 57, 61, 68], "head": [], "tf-idf": 1.1637419716080588}, "31/101": {"tf": 8, "body": [1271, 1279, 1317, 1363, 12678, 13259, 13267, 13291], "head": [], "tf-idf": 1.303557854439636}, "63/187": {"tf": 1, "body": [225], "head": [], "tf-idf": 0.6849691098948304}, "11/294": {"tf": 1, "body": [14], "head": [], "tf-idf": 0.6849691098948304}, "64/479": {"tf": 1, "body": [1034], "head": [], "tf-idf": 0.6849691098948304}, "42/477": {"tf": 1, "body": [49], "head": [], "tf-idf": 0.6849691098948304}, "73/357": {"tf": 1, "body": [56], "head": [], "tf-idf": 0.6849691098948304}, "63/62": {"tf": 5, "body": [228, 238, 246, 259, 846], "head": [], "tf-idf": 1.1637419716080588}, "30/492": {"tf": 1, "body": [32], "head": [], "tf-idf": 0.6849691098948304}, "56/20": {"tf": 2, "body": [24, 69], "head": [], "tf-idf": 0.8911653580764323}, "47/231": {"tf": 2, "body": [815, 823], "head": [], "tf-idf": 0.8911653580764323}, "68/389": {"tf": 5, "body": [4677, 5943, 9043, 11590, 16733], "head": [], "tf-idf": 1.1637419716080588}, "28/38": {"tf": 2, "body": [1, 6], "head": [], "tf-idf": 0.8911653580764323}, "32/178": {"tf": 1, "body": [24], "head": [], "tf-idf": 0.6849691098948304}, "56/461": {"tf": 2, "body": [41, 71], "head": [], "tf-idf": 0.8911653580764323}, "22/474": {"tf": 2, "body": [0], "head": [0], "tf-idf": 0.8911653580764323}, "1/40": {"tf": 1, "body": [13], "head": [], "tf-idf": 0.6849691098948304}, "22/434": {"tf": 1, "body": [79], "head": [], "tf-idf": 0.6849691098948304}, "58/252": {"tf": 4, "body": [180, 497, 542, 571], "head": [], "tf-idf": 1.0973616062580343}, "55/489": {"tf": 1, "body": [58], "head": [], "tf-idf": 0.6849691098948304}}], ["bipe", {"19/336": {"tf": 1, "body": [7670], "head": [], "tf-idf": 2.545307116465824}, "49/410": {"tf": 1, "body": [7081], "head": [], "tf-idf": 2.545307116465824}}], ["bipectin", {"19/336": {"tf": 1, "body": [26894], "head": [], "tf-idf": 2.545307116465824}, "49/410": {"tf": 1, "body": [7080], "head": [], "tf-idf": 2.545307116465824}}], ["biped", {"19/336": {"tf": 1, "body": [29400], "head": [], "tf-idf": 2.1473671077937864}, "12/91": {"tf": 2, "body": [3051, 3058], "head": [], "tf-idf": 2.7937890189419257}, "13/59": {"tf": 2, "body": [3443, 3472], "head": [], "tf-idf": 2.7937890189419257}, "30/230": {"tf": 2, "body": [3454, 3483], "head": [], "tf-idf": 2.7937890189419257}, "49/410": {"tf": 1, "body": [7082], "head": [], "tf-idf": 2.1473671077937864}}], ["bipelt", {"19/336": {"tf": 1, "body": [15459], "head": [], "tf-idf": 2.545307116465824}, "49/410": {"tf": 1, "body": [7083], "head": [], "tf-idf": 2.545307116465824}}], ["bipenn", {"19/336": {"tf": 1, "body": [15460], "head": [], "tf-idf": 2.545307116465824}, "49/410": {"tf": 1, "body": [7084], "head": [], "tf-idf": 2.545307116465824}}], ["bipeptid", {"33/162": {"tf": 1, "body": [34], "head": [], "tf-idf": 2.0681858617461617}, "11/35": {"tf": 1, "body": [67], "head": [], "tf-idf": 2.0681858617461617}, "17/115": {"tf": 1, "body": [67], "head": [], "tf-idf": 2.0681858617461617}, "17/15": {"tf": 1, "body": [45], "head": [], "tf-idf": 2.0681858617461617}, "56/354": {"tf": 1, "body": [60], "head": [], "tf-idf": 2.0681858617461617}, "26/282": {"tf": 1, "body": [52], "head": [], "tf-idf": 2.0681858617461617}}], ["biphas", {"12/43": {"tf": 1, "body": [191], "head": [], "tf-idf": 2.846337112129805}}], ["biphosph", {"40/459": {"tf": 1, "body": [23901], "head": [], "tf-idf": 2.0681858617461617}, "27/162": {"tf": 1, "body": [475], "head": [], "tf-idf": 2.0681858617461617}, "58/279": {"tf": 1, "body": [511], "head": [], "tf-idf": 2.0681858617461617}, "40/403": {"tf": 1, "body": [797], "head": [], "tf-idf": 2.0681858617461617}, "43/455": {"tf": 1, "body": [636], "head": [], "tf-idf": 2.0681858617461617}, "51/280": {"tf": 1, "body": [111], "head": [], "tf-idf": 2.0681858617461617}}], ["biphosphatas", {"40/459": {"tf": 1, "body": [11204], "head": [], "tf-idf": 1.8920946026904804}, "15/301": {"tf": 1, "body": [825], "head": [], "tf-idf": 1.8920946026904804}, "12/291": {"tf": 1, "body": [1030], "head": [], "tf-idf": 1.8920946026904804}, "62/198": {"tf": 1, "body": [183], "head": [], "tf-idf": 1.8920946026904804}, "57/103": {"tf": 1, "body": [430], "head": [], "tf-idf": 1.8920946026904804}, "73/201": {"tf": 1, "body": [333], "head": [], "tf-idf": 1.8920946026904804}, "62/22": {"tf": 1, "body": [480], "head": [], "tf-idf": 1.8920946026904804}, "58/130": {"tf": 1, "body": [229], "head": [], "tf-idf": 1.8920946026904804}, "48/345": {"tf": 1, "body": [17313], "head": [], "tf-idf": 1.8920946026904804}}], ["bipin", {"30/76": {"tf": 1, "body": [1194], "head": [], "tf-idf": 2.545307116465824}, "28/341": {"tf": 1, "body": [1077], "head": [], "tf-idf": 2.545307116465824}}], ["bipinn", {"19/336": {"tf": 1, "body": [15464], "head": [], "tf-idf": 2.545307116465824}, "49/410": {"tf": 1, "body": [7085], "head": [], "tf-idf": 2.545307116465824}}], ["bipinnatifid", {"19/336": {"tf": 1, "body": [15682], "head": [], "tf-idf": 2.545307116465824}, "49/410": {"tf": 1, "body": [7086], "head": [], "tf-idf": 2.545307116465824}}], ["biplan", {"19/336": {"tf": 1, "body": [19860], "head": [], "tf-idf": 2.545307116465824}, "49/410": {"tf": 1, "body": [7087], "head": [], "tf-idf": 2.545307116465824}}], ["biplanar", {"63/62": {"tf": 1, "body": [655], "head": [], "tf-idf": 2.846337112129805}}], ["bipolar", {"44/88": {"tf": 1, "body": [969], "head": [], "tf-idf": 1.3549754182955327}, "50/51": {"tf": 1, "body": [384], "head": [], "tf-idf": 1.3549754182955327}, "40/340": {"tf": 1, "body": [176], "head": [], "tf-idf": 1.3549754182955327}, "7/410": {"tf": 6, "body": [29259, 29263, 29265, 36584, 36588, 36590], "head": [], "tf-idf": 2.409351234281302}, "12/130": {"tf": 1, "body": [1045], "head": [], "tf-idf": 1.3549754182955327}, "55/118": {"tf": 3, "body": [318, 429, 674], "head": [], "tf-idf": 2.0014629899869965}, "27/339": {"tf": 1, "body": [544], "head": [], "tf-idf": 1.3549754182955327}, "56/489": {"tf": 1, "body": [838], "head": [], "tf-idf": 1.3549754182955327}, "63/142": {"tf": 2, "body": [1524, 16769], "head": [], "tf-idf": 1.7628636625898382}, "19/336": {"tf": 1, "body": [37962], "head": [], "tf-idf": 1.3549754182955327}, "6/270": {"tf": 3, "body": [216, 534, 652], "head": [], "tf-idf": 2.0014629899869965}, "9/95": {"tf": 1, "body": [584], "head": [], "tf-idf": 1.3549754182955327}, "68/57": {"tf": 2, "body": [515, 520], "head": [], "tf-idf": 1.7628636625898382}, "73/374": {"tf": 1, "body": [1078], "head": [], "tf-idf": 1.3549754182955327}, "69/366": {"tf": 2, "body": [1036, 6328], "head": [], "tf-idf": 1.7628636625898382}, "58/32": {"tf": 1, "body": [642], "head": [], "tf-idf": 1.3549754182955327}, "40/459": {"tf": 1, "body": [3249], "head": [], "tf-idf": 1.3549754182955327}, "13/328": {"tf": 1, "body": [179], "head": [], "tf-idf": 1.3549754182955327}, "48/45": {"tf": 3, "body": [214, 532, 650], "head": [], "tf-idf": 2.0014629899869965}, "59/383": {"tf": 1, "body": [96], "head": [], "tf-idf": 1.3549754182955327}, "64/44": {"tf": 1, "body": [152], "head": [], "tf-idf": 1.3549754182955327}, "31/407": {"tf": 1, "body": [521], "head": [], "tf-idf": 1.3549754182955327}, "45/31": {"tf": 2, "body": [290, 450], "head": [], "tf-idf": 1.7628636625898382}, "26/294": {"tf": 1, "body": [786], "head": [], "tf-idf": 1.3549754182955327}, "18/264": {"tf": 1, "body": [690], "head": [], "tf-idf": 1.3549754182955327}, "26/484": {"tf": 1, "body": [1043], "head": [], "tf-idf": 1.3549754182955327}, "49/410": {"tf": 1, "body": [7088], "head": [], "tf-idf": 1.3549754182955327}, "0/466": {"tf": 2, "body": [341, 1724], "head": [], "tf-idf": 1.7628636625898382}, "66/93": {"tf": 1, "body": [521], "head": [], "tf-idf": 1.3549754182955327}, "69/351": {"tf": 1, "body": [119], "head": [], "tf-idf": 1.3549754182955327}, "9/0": {"tf": 1, "body": [267], "head": [], "tf-idf": 1.3549754182955327}}], ["bipolym", {"13/109": {"tf": 1, "body": [160], "head": [], "tf-idf": 2.846337112129805}}], ["bipont", {"19/336": {"tf": 1, "body": [7787], "head": [], "tf-idf": 2.545307116465824}, "49/410": {"tf": 1, "body": [7089], "head": [], "tf-idf": 2.545307116465824}}], ["biprism", {"70/21": {"tf": 5, "body": [96, 102, 105, 134, 183], "head": [], "tf-idf": 3.812959509659935}, "33/420": {"tf": 1, "body": [334], "head": [], "tf-idf": 2.244277120801843}, "27/22": {"tf": 1, "body": [114], "head": [], "tf-idf": 2.244277120801843}, "71/363": {"tf": 1, "body": [91], "head": [], "tf-idf": 2.244277120801843}}], ["bipunct", {"19/336": {"tf": 1, "body": [43063], "head": [], "tf-idf": 2.545307116465824}, "49/410": {"tf": 1, "body": [7090], "head": [], "tf-idf": 2.545307116465824}}], ["bipush", {"26/411": {"tf": 9, "body": [269, 273, 277, 290, 294, 298, 312, 316, 320], "head": [], "tf-idf": 4.974147366575943}, "39/60": {"tf": 1, "body": [34], "head": [], "tf-idf": 2.545307116465824}}], ["bipyramid", {"10/36": {"tf": 1, "body": [156], "head": [], "tf-idf": 2.545307116465824}, "18/259": {"tf": 1, "body": [174], "head": [], "tf-idf": 2.545307116465824}}]]