[["rilassant", {"7/410": {"tf": 1, "body": [5205], "head": [], "tf-idf": 2.846337112129805}}], ["rilca", {"63/355": {"tf": 1, "body": [106], "head": [], "tf-idf": 2.846337112129805}}], ["rile", {"25/389": {"tf": 1, "body": [422], "head": [], "tf-idf": 2.846337112129805}}], ["rilett", {"18/340": {"tf": 2, "body": [13558, 13688], "head": [], "tf-idf": 3.703169960652469}}], ["rilevamento", {"11/286": {"tf": 1, "body": [7], "head": [], "tf-idf": 2.369215857410143}, "52/247": {"tf": 1, "body": [7], "head": [], "tf-idf": 2.369215857410143}, "41/399": {"tf": 1, "body": [3282], "head": [], "tf-idf": 2.369215857410143}}], ["riley", {"19/304": {"tf": 1, "body": [111], "head": [], "tf-idf": 1.9432471251378618}, "33/349": {"tf": 1, "body": [810], "head": [], "tf-idf": 1.9432471251378618}, "65/323": {"tf": 1, "body": [3505], "head": [], "tf-idf": 1.9432471251378618}, "26/447": {"tf": 1, "body": [4058], "head": [], "tf-idf": 1.9432471251378618}, "12/211": {"tf": 1, "body": [48], "head": [], "tf-idf": 1.9432471251378618}, "44/424": {"tf": 2, "body": [43075, 43078], "head": [], "tf-idf": 2.5282227987921564}, "55/367": {"tf": 1, "body": [2731], "head": [], "tf-idf": 1.9432471251378618}, "17/104": {"tf": 1, "body": [1361], "head": [], "tf-idf": 1.9432471251378618}}], ["rilievo", {"19/336": {"tf": 2, "body": [26603, 39406], "head": [], "tf-idf": 3.3115209066990317}, "49/410": {"tf": 2, "body": [10855, 44617], "head": [], "tf-idf": 3.3115209066990317}}], ["rilla", {"44/424": {"tf": 2, "body": [43081, 43084], "head": [], "tf-idf": 3.703169960652469}}], ["rilli", {"65/323": {"tf": 1, "body": [4384], "head": [], "tf-idf": 2.846337112129805}}], ["riloff", {"64/91": {"tf": 1, "body": [1850], "head": [], "tf-idf": 2.545307116465824}, "48/264": {"tf": 1, "body": [1618], "head": [], "tf-idf": 2.545307116465824}}]]