[["vra", {"59/415": {"tf": 1, "body": [8], "head": [], "tf-idf": 2.846337112129805}}], ["vrai", {"42/45": {"tf": 1, "body": [844], "head": [], "tf-idf": 2.545307116465824}, "65/38": {"tf": 5, "body": [12743, 12744, 12747, 12754, 22260], "head": [], "tf-idf": 4.32440044269844}}], ["vraiment", {"52/248": {"tf": 1, "body": [1035], "head": [], "tf-idf": 1.0904622564573139}, "41/119": {"tf": 1, "body": [1035], "head": [], "tf-idf": 1.0904622564573139}, "44/441": {"tf": 1, "body": [1035], "head": [], "tf-idf": 1.0904622564573139}, "38/134": {"tf": 1, "body": [1035], "head": [], "tf-idf": 1.0904622564573139}, "35/214": {"tf": 1, "body": [1035], "head": [], "tf-idf": 1.0904622564573139}, "22/74": {"tf": 1, "body": [1035], "head": [], "tf-idf": 1.0904622564573139}, "21/14": {"tf": 1, "body": [1035], "head": [], "tf-idf": 1.0904622564573139}, "45/140": {"tf": 1, "body": [1035], "head": [], "tf-idf": 1.0904622564573139}, "15/196": {"tf": 1, "body": [1035], "head": [], "tf-idf": 1.0904622564573139}, "36/121": {"tf": 1, "body": [1035], "head": [], "tf-idf": 1.0904622564573139}, "22/18": {"tf": 1, "body": [1035], "head": [], "tf-idf": 1.0904622564573139}, "13/399": {"tf": 1, "body": [1035], "head": [], "tf-idf": 1.0904622564573139}, "73/158": {"tf": 1, "body": [1035], "head": [], "tf-idf": 1.0904622564573139}, "51/376": {"tf": 1, "body": [1035], "head": [], "tf-idf": 1.0904622564573139}, "6/318": {"tf": 1, "body": [1035], "head": [], "tf-idf": 1.0904622564573139}, "9/55": {"tf": 1, "body": [1035], "head": [], "tf-idf": 1.0904622564573139}, "26/317": {"tf": 1, "body": [1035], "head": [], "tf-idf": 1.0904622564573139}, "12/203": {"tf": 1, "body": [1035], "head": [], "tf-idf": 1.0904622564573139}, "59/241": {"tf": 1, "body": [1035], "head": [], "tf-idf": 1.0904622564573139}, "57/52": {"tf": 1, "body": [1035], "head": [], "tf-idf": 1.0904622564573139}, "39/414": {"tf": 1, "body": [1035], "head": [], "tf-idf": 1.0904622564573139}, "9/463": {"tf": 1, "body": [1035], "head": [], "tf-idf": 1.0904622564573139}, "32/183": {"tf": 1, "body": [1035], "head": [], "tf-idf": 1.0904622564573139}, "14/329": {"tf": 1, "body": [1035], "head": [], "tf-idf": 1.0904622564573139}, "51/288": {"tf": 1, "body": [1035], "head": [], "tf-idf": 1.0904622564573139}, "10/116": {"tf": 1, "body": [1035], "head": [], "tf-idf": 1.0904622564573139}, "63/216": {"tf": 1, "body": [1035], "head": [], "tf-idf": 1.0904622564573139}, "34/368": {"tf": 1, "body": [1035], "head": [], "tf-idf": 1.0904622564573139}, "54/333": {"tf": 1, "body": [1035], "head": [], "tf-idf": 1.0904622564573139}, "57/251": {"tf": 1, "body": [1035], "head": [], "tf-idf": 1.0904622564573139}, "66/117": {"tf": 1, "body": [1035], "head": [], "tf-idf": 1.0904622564573139}, "35/168": {"tf": 1, "body": [1035], "head": [], "tf-idf": 1.0904622564573139}, "5/174": {"tf": 1, "body": [1035], "head": [], "tf-idf": 1.0904622564573139}, "18/415": {"tf": 1, "body": [1035], "head": [], "tf-idf": 1.0904622564573139}, "14/432": {"tf": 1, "body": [1035], "head": [], "tf-idf": 1.0904622564573139}, "56/492": {"tf": 1, "body": [1035], "head": [], "tf-idf": 1.0904622564573139}, "1/484": {"tf": 1, "body": [1035], "head": [], "tf-idf": 1.0904622564573139}, "26/394": {"tf": 1, "body": [1035], "head": [], "tf-idf": 1.0904622564573139}, "11/377": {"tf": 1, "body": [1035], "head": [], "tf-idf": 1.0904622564573139}, "9/67": {"tf": 1, "body": [1035], "head": [], "tf-idf": 1.0904622564573139}, "40/351": {"tf": 1, "body": [1035], "head": [], "tf-idf": 1.0904622564573139}, "48/143": {"tf": 1, "body": [1035], "head": [], "tf-idf": 1.0904622564573139}, "20/424": {"tf": 1, "body": [1035], "head": [], "tf-idf": 1.0904622564573139}, "50/386": {"tf": 1, "body": [1035], "head": [], "tf-idf": 1.0904622564573139}, "68/82": {"tf": 1, "body": [1035], "head": [], "tf-idf": 1.0904622564573139}, "12/322": {"tf": 1, "body": [1035], "head": [], "tf-idf": 1.0904622564573139}, "38/98": {"tf": 1, "body": [1035], "head": [], "tf-idf": 1.0904622564573139}, "14/429": {"tf": 1, "body": [1035], "head": [], "tf-idf": 1.0904622564573139}, "48/39": {"tf": 1, "body": [1035], "head": [], "tf-idf": 1.0904622564573139}, "55/59": {"tf": 1, "body": [1035], "head": [], "tf-idf": 1.0904622564573139}, "11/0": {"tf": 1, "body": [1035], "head": [], "tf-idf": 1.0904622564573139}, "22/452": {"tf": 1, "body": [1035], "head": [], "tf-idf": 1.0904622564573139}, "15/125": {"tf": 1, "body": [1035], "head": [], "tf-idf": 1.0904622564573139}, "71/336": {"tf": 1, "body": [1035], "head": [], "tf-idf": 1.0904622564573139}, "39/351": {"tf": 1, "body": [1035], "head": [], "tf-idf": 1.0904622564573139}, "30/373": {"tf": 1, "body": [1035], "head": [], "tf-idf": 1.0904622564573139}, "41/215": {"tf": 1, "body": [1035], "head": [], "tf-idf": 1.0904622564573139}}], ["vrajakum", {"7/292": {"tf": 1, "body": [87], "head": [], "tf-idf": 2.545307116465824}, "5/63": {"tf": 1, "body": [38], "head": [], "tf-idf": 2.545307116465824}}], ["vraje0c", {"65/135": {"tf": 1, "body": [9], "head": [], "tf-idf": 2.846337112129805}}], ["vraman", {"74/218": {"tf": 2, "body": [11, 12], "head": [], "tf-idf": 3.703169960652469}}], ["vranizan", {"0/379": {"tf": 1, "body": [322], "head": [], "tf-idf": 2.846337112129805}}], ["vranov", {"20/20": {"tf": 3, "body": [4192, 4236, 5344], "head": [], "tf-idf": 4.204385046424318}}], ["vraptor", {"39/373": {"tf": 33, "body": [6668, 6676, 6685, 6696, 6707, 6717, 6726, 6737, 6748, 6758, 6767, 6778, 6789, 6799, 6808, 6819, 6830, 6840, 6849, 6860, 6871, 6881, 6890, 6901, 6912, 6922, 6931, 6942, 6953, 6963, 6972, 6983, 6994], "head": [], "tf-idf": 7.168539694490684}}], ["vrar", {"33/329": {"tf": 2, "body": [545, 561], "head": [], "tf-idf": 3.0824208966933537}, "47/446": {"tf": 2, "body": [539, 548], "head": [], "tf-idf": 3.0824208966933537}, "47/447": {"tf": 2, "body": [539, 548], "head": [], "tf-idf": 3.0824208966933537}}]]